xlogitprit/__init__.py
xlogitprit/_choice_model.py
xlogitprit/_device.py
xlogitprit/boxcox_functions.py
xlogitprit/latent_class_model.py
xlogitprit/latent_class_model2.py
xlogitprit/latent_class_model_mixed.py
xlogitprit/mixed_logit.py
xlogitprit/multinomial_logit.py
xlogitprit/__pycache__/__init__.cpython-38.pyc
xlogitprit/__pycache__/_choice_model.cpython-38.pyc
xlogitprit/__pycache__/_device.cpython-38.pyc
xlogitprit/__pycache__/boxcox_functions.cpython-38.pyc
xlogitprit/__pycache__/mixed_logit.cpython-38.pyc
xlogitprit/__pycache__/multinomial_logit.cpython-38.pyc
xlogitprit-0.1.34.dist-info/LICENSE
xlogitprit-0.1.34.dist-info/METADATA
xlogitprit-0.1.34.dist-info/WHEEL
xlogitprit-0.1.34.dist-info/top_level.txt
xlogitprit-0.1.34.dist-info/RECORD
