Metadata-Version: 2.1
Name: xlogitprit
Version: 0.1.34
Summary: A Python package for GPU-accelerated estimation of mixed logit models.
Home-page: https://github.com/PrithviBhatB/xlogit
Author: Ryan Kelly
Author-email: ryan@kiiii.com
License: MIT
Platform: UNKNOWN
Requires-Python: >=3.5
Requires-Dist: numpy (>=1.13.1)
Requires-Dist: scipy (>=1.0.0)
